omada_client/__init__.py
omada_client/client.py
omada_client/types.py
omada_client-1.2.22.dist-info/licenses/LICENSE
tests/__init__.py
tests/test_client.py
tests/test_data.py
omada_client-1.2.22.dist-info/METADATA
omada_client-1.2.22.dist-info/WHEEL
omada_client-1.2.22.dist-info/top_level.txt
omada_client-1.2.22.dist-info/RECORD
