Metadata-Version: 2.4
Name: omada_client
Version: 1.2.22
Summary: Execute API calls to Omada Controller from python code
Author-email: Erilov Nikita <minitwiks@gmail.com>
License: MIT
Project-URL: homepage, https://github.com/ErilovNikita/omada-client
Classifier: Development Status :: 5 - Production/Stable
Classifier: Intended Audience :: Developers
Classifier: Intended Audience :: System Administrators
Classifier: Programming Language :: Python
Classifier: Programming Language :: Python :: 3.11
Classifier: Programming Language :: Python :: 3.12
Classifier: Programming Language :: Python :: 3.13
Classifier: Programming Language :: Python :: 3.14
Requires-Python: >=3.11
License-File: LICENSE
Requires-Dist: requests==2.32.3
Requires-Dist: urllib3==2.2.3
Requires-Dist: pydantic==2.9.2
Requires-Dist: dotenv==0.9.9
Provides-Extra: dev
Requires-Dist: pytest==8.4.2; extra == "dev"
Requires-Dist: pytest-asyncio==1.2.0; extra == "dev"
Requires-Dist: pytest-cov==7.0.0; extra == "dev"
Requires-Dist: requests-mock==1.12.1; extra == "dev"
Dynamic: license-file
